kq/__init__.py
kq/job.py
kq/message.py
kq/queue.py
kq/utils.py
kq/version.py
kq/worker.py
kq-2.2.1.dist-info/LICENSE
kq-2.2.1.dist-info/METADATA
kq-2.2.1.dist-info/WHEEL
kq-2.2.1.dist-info/top_level.txt
kq-2.2.1.dist-info/RECORD
